hnr_investimento-0.1.dist-info/licenses/LICENSE
investimentos/__init__.py
investimentos/investimentos.py
hnr_investimento-0.1.dist-info/METADATA
hnr_investimento-0.1.dist-info/WHEEL
hnr_investimento-0.1.dist-info/top_level.txt
hnr_investimento-0.1.dist-info/RECORD
