Metadata-Version: 2.4
Name: hnr_investimento
Version: 0.1
Summary: Uma biblioteca para cálculos de investimentos.
Home-page: https://github.com/henriquecomp/investpy
Author: Henrique F Tambalo
Author-email: henrique.comp@gmail.com
Classifier: Programming Language :: Python :: 3
Classifier: License :: OSI Approved :: MIT License
Classifier: Operating System :: OS Independent
Requires-Python: >=3.6
License-File: LICENSE
Dynamic: author
Dynamic: author-email
Dynamic: classifier
Dynamic: home-page
Dynamic: license-file
Dynamic: requires-python
Dynamic: summary
